palm/plugins/dbt/__init__.py
palm/plugins/dbt/dbt_containerizer.py
palm/plugins/dbt/dbt_palm_utils.py
palm/plugins/dbt/dbt_plugin.py
palm/plugins/dbt/dbt_version_detection.py
palm/plugins/dbt/local_user_lookup.py
palm/plugins/dbt/plugin_config.py
palm/plugins/dbt/requirements.txt
palm/plugins/dbt/sql_to_dbt.py
palm/plugins/dbt/commands/__init__.py
palm/plugins/dbt/commands/cmd_cleanup.py
palm/plugins/dbt/commands/cmd_compile.py
palm/plugins/dbt/commands/cmd_containerize.py
palm/plugins/dbt/commands/cmd_cycle.py
palm/plugins/dbt/commands/cmd_dbt-docs.py
palm/plugins/dbt/commands/cmd_dbt.py
palm/plugins/dbt/commands/cmd_install.py
palm/plugins/dbt/commands/cmd_model-doc.py
palm/plugins/dbt/commands/cmd_model.py
palm/plugins/dbt/commands/cmd_prod-artifacts.py
palm/plugins/dbt/commands/cmd_run.py
palm/plugins/dbt/commands/cmd_seed.py
palm/plugins/dbt/commands/cmd_shell.py
palm/plugins/dbt/commands/cmd_snapshot.py
palm/plugins/dbt/commands/cmd_test.py
palm/plugins/dbt/macros/drop_branch_schemas.sql
palm/plugins/dbt/macros/generate_schema_name.sql
palm/plugins/dbt/model_template/docs/base_model.md
palm/plugins/dbt/model_template/docs/template-config.yaml
palm/plugins/dbt/model_template/model/base_model.sql
palm/plugins/dbt/model_template/model/base_model.yml
palm/plugins/dbt/model_template/model/template-config.yaml
palm/plugins/dbt/model_template/ref_files/ref_file.sql
palm/plugins/dbt/model_template/ref_files/ref_file_readme.md
palm/plugins/dbt/parsers/__init__.py
palm/plugins/dbt/parsers/project_parser.py
palm/plugins/dbt/templates/containerize/Dockerfile.txt
palm/plugins/dbt/templates/containerize/docker-compose.yaml
palm/plugins/dbt/templates/containerize/entrypoint.sh.txt
palm/plugins/dbt/templates/containerize/template-config.yaml
palm/plugins/dbt/templates/model_docs/model_doc.tpl.md
palm/plugins/dbt/templates/model_docs/template-config.yaml
palm_dbt-0.8.0.dist-info/LICENSE
palm_dbt-0.8.0.dist-info/METADATA
palm_dbt-0.8.0.dist-info/WHEEL
palm_dbt-0.8.0.dist-info/top_level.txt
palm_dbt-0.8.0.dist-info/RECORD
