Metadata-Version: 2.1
Name: palm-dbt
Version: 0.8.0
Summary: dbt extension for Palm CLI
Home-page: https://github.com/palmetto/palm-dbt
Author: Palmetto - Data & Analytics team
Author-email: data-analytics-team@palmetto.com
License: Apache License 2.0
Platform: UNKNOWN
Classifier: Development Status :: 4 - Beta
Classifier: License :: OSI Approved :: Apache Software License
License-File: LICENSE
Requires-Dist: palm (<3.0,>=2.6.0)
Requires-Dist: pyyaml (>=5.0)
Requires-Dist: semver (>=3.0.1)
Requires-Dist: sqlparse (>=0.3.1)
